multimodal_agent/__init__.py
multimodal_agent/agent_core.py
multimodal_agent/config.py
multimodal_agent/errors.py
multimodal_agent/logger.py
multimodal_agent/utils.py
multimodal_agent/version.py
multimodal_agent/cli/__init__.py
multimodal_agent/cli/cli.py
multimodal_agent/cli/formatting.py
multimodal_agent/cli/history.py
multimodal_agent/cli/printing.py
multimodal_agent/codegen/__init__.py
multimodal_agent/codegen/engine.py
multimodal_agent/codegen/enum_template.py
multimodal_agent/codegen/generator.py
multimodal_agent/codegen/model_template.py
multimodal_agent/codegen/repository_template.py
multimodal_agent/codegen/screen_template.py
multimodal_agent/codegen/utils.py
multimodal_agent/codegen/widget_template.py
multimodal_agent/core/__init__.py
multimodal_agent/core/agent_core.py
multimodal_agent/core/embedding.py
multimodal_agent/core/tokenizer.py
multimodal_agent/deprecated/__init__.py
multimodal_agent/deprecated/json_memory.py
multimodal_agent/project_scanner/__init__.py
multimodal_agent/project_scanner/ingest.py
multimodal_agent/project_scanner/project_style.py
multimodal_agent/project_scanner/scanner.py
multimodal_agent/project_scanner/style_profile.py
multimodal_agent/rag/__init__.py
multimodal_agent/rag/chunking.py
multimodal_agent/rag/rag_store.py
multimodal_agent/server/__init__.py
multimodal_agent/server/server.py
multimodal_agent/server/server_models.py
multimodal_agent/tests/conftest.py
multimodal_agent/tests/test_utils_images.py
multimodal_agent/tests/cli/test_cli.py
multimodal_agent/tests/cli/test_cli_codegen.py
multimodal_agent/tests/cli/test_cli_formatting.py
multimodal_agent/tests/cli/test_cli_history.py
multimodal_agent/tests/cli/test_cli_image_formatting.py
multimodal_agent/tests/cli/test_cli_learn_project.py
multimodal_agent/tests/cli/test_detect_language.py
multimodal_agent/tests/cli/test_formatting.py
multimodal_agent/tests/cli/test_history.py
multimodal_agent/tests/cli/test_learn_commands.py
multimodal_agent-0.9.0.dist-info/licenses/LICENSE
multimodal_agent-0.9.0.dist-info/METADATA
multimodal_agent-0.9.0.dist-info/WHEEL
multimodal_agent-0.9.0.dist-info/entry_points.txt
multimodal_agent-0.9.0.dist-info/top_level.txt
multimodal_agent-0.9.0.dist-info/RECORD
