Metadata-Version: 2.4
Name: multimodal-agent
Version: 0.9.0
Summary: A Python multimodal agent for interacting with Gemini models via text, images, and CLI.
Author-email: Horam <horam.tech@google.com>
License-Expression: MIT
Requires-Python: >=3.10
License-File: LICENSE
Requires-Dist: google-genai>=1.45.0
Requires-Dist: python-dotenv>=1.0.0
Requires-Dist: requests>=2.31.0
Requires-Dist: Pillow>=10.0.0
Provides-Extra: test
Requires-Dist: pytest>=7.4; extra == "test"
Requires-Dist: pytest-mock>=3.12; extra == "test"
Requires-Dist: pytest-cov>=4.1; extra == "test"
Provides-Extra: dev
Requires-Dist: pytest>=7.4; extra == "dev"
Requires-Dist: pytest-mock>=3.12; extra == "dev"
Requires-Dist: pytest-cov>=4.1; extra == "dev"
Requires-Dist: black>=24.0; extra == "dev"
Requires-Dist: flake8>=7.0; extra == "dev"
Requires-Dist: isort>=5.13; extra == "dev"
Requires-Dist: mkdocs>=1.6; extra == "dev"
Requires-Dist: mkdocs-material>=9.5; extra == "dev"
Requires-Dist: mkdocstrings[python]; extra == "dev"
Dynamic: license-file
